auth0_api_client/__init__.py
auth0_api_client/authz.py
auth0_api_client/config.py
auth0_api_client/errors.py
auth0_api_client/jwt.py
auth0_api_client/mgmt.py
auth0_api_client/models/__init__.py
auth0_api_client/models/group.py
auth0_api_client/models/permission.py
auth0_api_client/models/role.py
auth0_api_client/py.typed
auth0_api_client/rate_limit_handler.py
auth0_api_client-1.3.6.dist-info/LICENSE.md
auth0_api_client-1.3.6.dist-info/WHEEL
auth0_api_client-1.3.6.dist-info/METADATA
auth0_api_client-1.3.6.dist-info/RECORD
