Metadata-Version: 2.1
Name: auth0-api-client
Version: 1.3.6
Summary: Client library for Auth0 management API
Home-page: https://github.com/polaris-foundation/auth0-api-client
Keywords: Polaris,Auth0,API,Management
Author: Jon Daly
Author-email: jonathan.daly@sensynehealth.com
Requires-Python: >=3.8,<4.0
Classifier: Programming Language :: Python :: 3
Classifier: Programming Language :: Python :: 3.10
Classifier: Programming Language :: Python :: 3.8
Classifier: Programming Language :: Python :: 3.9
Requires-Dist: environs (>=9.0.0,<10.0.0)
Requires-Dist: requests (>=2.0.0,<3.0.0)
Requires-Dist: she-logging (>=1.0.0,<2.0.0)
Project-URL: Repository, https://github.com/polaris-foundation/auth0-api-client
